makeapp/__init__.py
makeapp/appconfig.py
makeapp/appmaker.py
makeapp/apptemplate.py
makeapp/apptools.py
makeapp/cli.py
makeapp/exceptions.py
makeapp/rendering.py
makeapp/utils.py
makeapp/app_templates/__default__/.gitignore
makeapp/app_templates/__default__/AUTHORS.md
makeapp/app_templates/__default__/CHANGELOG.md
makeapp/app_templates/__default__/CONTRIBUTING.md
makeapp/app_templates/__default__/INSTALL.md
makeapp/app_templates/__default__/README.md
makeapp/app_templates/__default__/mkdocs.yml
makeapp/app_templates/__default__/pyproject.toml
makeapp/app_templates/__default__/ruff.toml
makeapp/app_templates/__default__/docs/index.md
makeapp/app_templates/__default__/docs/quickstart.md
makeapp/app_templates/__default__/src/__package_name__/__init__.py
makeapp/app_templates/__default__/tests/__init__.py
makeapp/app_templates/__default__/tests/test_basic.py
makeapp/app_templates/click/makeappconf.py
makeapp/app_templates/click/pyproject.toml
makeapp/app_templates/click/src/__package_name__/cli.py
makeapp/app_templates/console/pyproject.toml
makeapp/app_templates/console/src/__package_name__/cli.py
makeapp/app_templates/django/makeappconf.py
makeapp/app_templates/django/pyproject.toml
makeapp/app_templates/django/.github/workflows/python-package.yml
makeapp/app_templates/django/src/__package_name__/__init__.py
makeapp/app_templates/django/src/__package_name__/admin.py
makeapp/app_templates/django/src/__package_name__/apps.py
makeapp/app_templates/django/src/__package_name__/models.py
makeapp/app_templates/django/src/__package_name__/views.py
makeapp/app_templates/django/src/__package_name__/locale/empty
makeapp/app_templates/django/src/__package_name__/management/__init__.py
makeapp/app_templates/django/src/__package_name__/management/commands/__init__.py
makeapp/app_templates/django/src/__package_name__/templates/empty
makeapp/app_templates/django/src/__package_name__/templatetags/empty
makeapp/app_templates/django/src/__package_name__/tests/__init__.py
makeapp-2.1.0.dist-info/METADATA
makeapp-2.1.0.dist-info/WHEEL
makeapp-2.1.0.dist-info/entry_points.txt
makeapp-2.1.0.dist-info/licenses/LICENSE
makeapp-2.1.0.dist-info/RECORD
