Metadata-Version: 2.4
Name: makeapp
Version: 2.1.0
Summary: Simplifies routine Python application development processes.
Project-URL: Homepage, https://github.com/idlesign/makeapp
Project-URL: Documentation, https://makeapp.readthedocs.io/
Author-email: Igor Starikov <idlesign@yandex.ru>
License-Expression: BSD-3-Clause
License-File: LICENSE
Keywords: development,scaffolding
Requires-Python: >=3.10
Requires-Dist: click
Requires-Dist: jinja2~=3.1
Requires-Dist: requests
